machathon_judge/__init__.py
machathon_judge/collision_manager.py
machathon_judge/data.py
machathon_judge/judge.py
machathon_judge/simulator.py
machathon_judge/zmqRemoteApi/__init__.py
machathon_judge-1.0.0.dist-info/LICENSE
machathon_judge-1.0.0.dist-info/METADATA
machathon_judge-1.0.0.dist-info/WHEEL
machathon_judge-1.0.0.dist-info/top_level.txt
machathon_judge-1.0.0.dist-info/RECORD
