Metadata-Version: 2.1
Name: machathon-judge
Version: 1.0.0
Summary: Judge library used for evaluating the first phase in the Machathon 4.0 competition
Author-email: STP <stp23.official@gmail.com>
License: MIT License
Keywords: machathon,stp,autonomous,coppelia
Classifier: License :: OSI Approved :: MIT License
Classifier: Programming Language :: Python
Classifier: Programming Language :: Python :: 3
Requires-Python: >=3.7
License-File: LICENSE
Requires-Dist: pyzmq
Requires-Dist: cbor
Requires-Dist: numpy
Requires-Dist: requests
Requires-Dist: websockets
